{
  "format": "vc_demo_run_manifest.v1",
  "created_at": "2026-07-20T10:29:57.700856+00:00",
  "experiment": "k562_feedback_guard_clean_full_run",
  "run_dir": "experiments/k562_feedback_guard_clean_full_run",
  "git": {
    "branch": "k562-feedback-guard-clean-full-run",
    "commit": "7ac7448660037896204653ab1f456d244ce3edc7",
    "status_short": "?? experiments/k562_best_child_multiseed_validation/\n?? experiments/k562_feedback_guard_clean_full_run/\n?? experiments/k562_full_global_queue_run/\n?? experiments/k562_generic_transfer_full_rerun_v2/\n?? experiments/official_k562_generic_transfer_v1/"
  },
  "search": {
    "selection_policy": "uct",
    "exploration": 1.4142135623730951,
    "budget_nodes": 2,
    "max_children": 10,
    "max_epochs": 8,
    "stop_no_improve": 60,
    "allow_planned_blueprints": true,
    "allow_missing_artifact_fallbacks": false,
    "artifact_aware_blueprint_policy": false,
    "stop_reason": "pending implementation trained"
  },
  "artifacts": {
    "registry_path": "configs/artifacts/k562_registry.json",
    "present_artifacts": [
      "string_k562_gene_graph",
      "pathway_membership_matrix",
      "official_essential_deg_with_split_h5ad",
      "official_k562_aido_cell_100m_embedding_h5ad",
      "official_string_gnn_keep20_graph",
      "official_gnn_simple_embedding_h5ad",
      "official_public_best_node_code",
      "class_distribution"
    ],
    "missing_artifacts": [
      "esm2_gene_embedding_h5ad",
      "esm2_k562_target_manifest",
      "aido_gene_or_cell_embeddings",
      "scfoundation_cell_embeddings",
      "official_aido_cell_100m_model_dir",
      "official_string_gnn_model_dir",
      "regulatory_network_artifact",
      "single_cell_foundation_model_artifact"
    ]
  },
  "queues": {
    "implementation_queue": "experiments/k562_feedback_guard_clean_full_run/implementation_queue.json",
    "acquisition_queue": "experiments/k562_feedback_guard_clean_full_run/acquisition_queue.json",
    "artifact_acquisition_command": "python -m vc_demo.harness.artifact_acquisition --queue experiments/k562_feedback_guard_clean_full_run/acquisition_queue.json --registry configs/artifacts/k562_registry.json --sources configs/artifacts/acquisition_sources.json --cell-line K562 --output-dir experiments/k562_feedback_guard_clean_full_run/artifact_acquisition --execute-known"
  },
  "results": {
    "trained_nodes": 24,
    "failed_nodes": 0,
    "best_node": "official_k562_root_aido_gnn_embedding_mlp",
    "best_val_macro_f1": 0.49353158473968506,
    "best_test_macro_f1": 0.5434165596961975,
    "best_root": "official_k562_root_aido_gnn_embedding_mlp",
    "best_root_val_macro_f1": 0.49353158473968506,
    "best_root_test_macro_f1": 0.5434165596961975,
    "last_manual_train_pending_node": "official_k562_root_aido_gnn_embedding_mlp_p6_official_target_low_rank_head_4ca91b75",
    "last_manual_train_pending_val_macro_f1": 0.48288118839263916,
    "last_manual_train_pending_test_macro_f1": 0.5301808714866638
  },
  "mcts": {
    "last_selection": {
      "node": "official_k562_root_aido_gnn_embedding_mlp_p10_official_target_graph_conditioned_head_cc233d73",
      "policy": "uct",
      "score": 2.455703761057494,
      "uct": 2.455703761057494,
      "puct": null,
      "q": 0.4935244619846344,
      "Q_v": 0.9870489239692688,
      "exploitation": 0.4935244619846344,
      "Exploitation": 0.4935244619846344,
      "exploration": 1.9621792990728597,
      "Exploration": 1.9621792990728597,
      "prior": 0.0,
      "visits": 2,
      "parent_visits": 47,
      "children": 6,
      "best_val_macro_f1": 0.4935244619846344,
      "stage": "improve"
    },
    "last_candidates": [
      {
        "node": "official_k562_root_aido_gnn_embedding_mlp_p10_official_target_graph_conditioned_head_cc233d73",
        "policy": "uct",
        "score": 2.455703761057494,
        "uct": 2.455703761057494,
        "puct": null,
        "q": 0.4935244619846344,
        "Q_v": 0.9870489239692688,
        "exploitation": 0.4935244619846344,
        "Exploitation": 0.4935244619846344,
        "exploration": 1.9621792990728597,
        "Exploration": 1.9621792990728597,
        "prior": 0.0,
        "visits": 2,
        "parent_visits": 47,
        "children": 6,
        "best_val_macro_f1": 0.4935244619846344,
        "stage": "improve"
      },
      {
        "node": "official_k562_root_aido_gnn_embedding_mlp_p8_official_target_bilinear_head_495e575b",
        "policy": "uct",
        "score": 2.450047995524047,
        "uct": 2.450047995524047,
        "puct": null,
        "q": 0.48786869645118713,
        "Q_v": 0.9757373929023743,
        "exploitation": 0.48786869645118713,
        "Exploitation": 0.48786869645118713,
        "exploration": 1.9621792990728597,
        "Exploration": 1.9621792990728597,
        "prior": 0.0,
        "visits": 2,
        "parent_visits": 47,
        "children": 0,
        "best_val_macro_f1": 0.48786869645118713,
        "stage": "improve"
      },
      {
        "node": "official_k562_root_aido_gnn_embedding_mlp_p8_official_string_neighborhood_attention_62af14f5",
        "policy": "uct",
        "score": 2.44632801003897,
        "uct": 2.44632801003897,
        "puct": null,
        "q": 0.48414871096611023,
        "Q_v": 0.9682974219322205,
        "exploitation": 0.48414871096611023,
        "Exploitation": 0.48414871096611023,
        "exploration": 1.9621792990728597,
        "Exploration": 1.9621792990728597,
        "prior": 0.0,
        "visits": 2,
        "parent_visits": 47,
        "children": 6,
        "best_val_macro_f1": 0.48414871096611023,
        "stage": "improve"
      },
      {
        "node": "official_k562_root_aido_gnn_embedding_mlp_p4_official_target_gene_head_68ad862b",
        "policy": "uct",
        "score": 2.441706265883086,
        "uct": 2.441706265883086,
        "puct": null,
        "q": 0.47952696681022644,
        "Q_v": 0.9590539336204529,
        "exploitation": 0.47952696681022644,
        "Exploitation": 0.47952696681022644,
        "exploration": 1.9621792990728597,
        "Exploration": 1.9621792990728597,
        "prior": 0.0,
        "visits": 2,
        "parent_visits": 47,
        "children": 0,
        "best_val_macro_f1": 0.47952696681022644,
        "stage": "improve"
      },
      {
        "node": "official_k562_root_aido_gnn_embedding_mlp_p11_official_pathway_pooling_reactome_6cb04fc4",
        "policy": "uct",
        "score": 2.4340249259039144,
        "uct": 2.4340249259039144,
        "puct": null,
        "q": 0.4718456268310547,
        "Q_v": 0.9436912536621094,
        "exploitation": 0.4718456268310547,
        "Exploitation": 0.4718456268310547,
        "exploration": 1.9621792990728597,
        "Exploration": 1.9621792990728597,
        "prior": 0.0,
        "visits": 2,
        "parent_visits": 47,
        "children": 0,
        "best_val_macro_f1": 0.4718456268310547,
        "stage": "improve"
      },
      {
        "node": "official_k562_root_aido_embedding_mlp_p6_official_target_low_rank_head_f28a1bc1",
        "policy": "uct",
        "score": 2.405345048384307,
        "uct": 2.405345048384307,
        "puct": null,
        "q": 0.44316574931144714,
        "Q_v": 0.8863314986228943,
        "exploitation": 0.44316574931144714,
        "Exploitation": 0.44316574931144714,
        "exploration": 1.9621792990728597,
        "Exploration": 1.9621792990728597,
        "prior": 0.0,
        "visits": 2,
        "parent_visits": 47,
        "children": 0,
        "best_val_macro_f1": 0.44316574931144714,
        "stage": "improve"
      },
      {
        "node": "official_k562_root_aido_embedding_mlp_p1_official_string_neighborhood_attention_a25d8fa1",
        "policy": "uct",
        "score": 2.405002977327941,
        "uct": 2.405002977327941,
        "puct": null,
        "q": 0.4428236782550812,
        "Q_v": 0.8856473565101624,
        "exploitation": 0.4428236782550812,
        "Exploitation": 0.4428236782550812,
        "exploration": 1.9621792990728597,
        "Exploration": 1.9621792990728597,
        "prior": 0.0,
        "visits": 2,
        "parent_visits": 47,
        "children": 0,
        "best_val_macro_f1": 0.4428236782550812,
        "stage": "improve"
      },
      {
        "node": "official_k562_root_aido_embedding_mlp_p10_official_gene_dropout_augmentation_ed174d61",
        "policy": "uct",
        "score": 2.382803316788314,
        "uct": 2.382803316788314,
        "puct": null,
        "q": 0.4206240177154541,
        "Q_v": 0.8412480354309082,
        "exploitation": 0.4206240177154541,
        "Exploitation": 0.4206240177154541,
        "exploration": 1.9621792990728597,
        "Exploration": 1.9621792990728597,
        "prior": 0.0,
        "visits": 2,
        "parent_visits": 47,
        "children": 0,
        "best_val_macro_f1": 0.4206240177154541,
        "stage": "improve"
      },
      {
        "node": "official_k562_root_aido_embedding_mlp_p9_official_multimodal_mixture_of_experts_4c5d0049",
        "policy": "uct",
        "score": 2.381302740053771,
        "uct": 2.381302740053771,
        "puct": null,
        "q": 0.41912344098091125,
        "Q_v": 0.8382468819618225,
        "exploitation": 0.41912344098091125,
        "Exploitation": 0.41912344098091125,
        "exploration": 1.9621792990728597,
        "Exploration": 1.9621792990728597,
        "prior": 0.0,
        "visits": 2,
        "parent_visits": 47,
        "children": 0,
        "best_val_macro_f1": 0.41912344098091125,
        "stage": "improve"
      },
      {
        "node": "official_k562_root_aido_embedding_mlp_p1_official_target_bilinear_head_217a17b9",
        "policy": "uct",
        "score": 2.3716613907381277,
        "uct": 2.3716613907381277,
        "puct": null,
        "q": 0.40948209166526794,
        "Q_v": 0.8189641833305359,
        "exploitation": 0.40948209166526794,
        "Exploitation": 0.40948209166526794,
        "exploration": 1.9621792990728597,
        "Exploration": 1.9621792990728597,
        "prior": 0.0,
        "visits": 2,
        "parent_visits": 47,
        "children": 0,
        "best_val_macro_f1": 0.40948209166526794,
        "stage": "improve"
      },
      {
        "node": "official_k562_root_aido_embedding_mlp_p2_official_focal_loss_training_37672209",
        "policy": "uct",
        "score": 2.3697259385153036,
        "uct": 2.3697259385153036,
        "puct": null,
        "q": 0.40754663944244385,
        "Q_v": 0.8150932788848877,
        "exploitation": 0.40754663944244385,
        "Exploitation": 0.40754663944244385,
        "exploration": 1.9621792990728597,
        "Exploration": 1.9621792990728597,
        "prior": 0.0,
        "visits": 2,
        "parent_visits": 47,
        "children": 0,
        "best_val_macro_f1": 0.40754663944244385,
        "stage": "improve"
      },
      {
        "node": "official_k562_root_aido_embedding_mlp_p11_official_temperature_calibrated_head_ddceef70",
        "policy": "uct",
        "score": 2.35757290907347,
        "uct": 2.35757290907347,
        "puct": null,
        "q": 0.39539361000061035,
        "Q_v": 0.7907872200012207,
        "exploitation": 0.39539361000061035,
        "Exploitation": 0.39539361000061035,
        "exploration": 1.9621792990728597,
        "Exploration": 1.9621792990728597,
        "prior": 0.0,
        "visits": 2,
        "parent_visits": 47,
        "children": 0,
        "best_val_macro_f1": 0.39539361000061035,
        "stage": "improve"
      },
      {
        "node": "official_k562_root_aido_embedding_mlp",
        "policy": "uct",
        "score": 1.2999460038569821,
        "uct": 1.2999460038569821,
        "puct": null,
        "q": 0.42243274450302126,
        "Q_v": 4.224327445030212,
        "exploitation": 0.42243274450302126,
        "Exploitation": 0.42243274450302126,
        "exploration": 0.8775132593539609,
        "Exploration": 0.8775132593539609,
        "prior": 0.0,
        "visits": 10,
        "parent_visits": 47,
        "children": 6,
        "best_val_macro_f1": 0.43374624848365784,
        "stage": "draft"
      },
      {
        "node": "official_k562_root_aido_gnn_embedding_mlp",
        "policy": "uct",
        "score": 1.2548175808521638,
        "uct": 1.2548175808521638,
        "puct": null,
        "q": 0.4851875396875235,
        "Q_v": 6.307438015937805,
        "exploitation": 0.4851875396875235,
        "Exploitation": 0.4851875396875235,
        "exploration": 0.7696300411646403,
        "Exploration": 0.7696300411646403,
        "prior": 0.0,
        "visits": 13,
        "parent_visits": 47,
        "children": 6,
        "best_val_macro_f1": 0.49353158473968506,
        "stage": "draft"
      }
    ],
    "selection_policy": "uct",
    "exploration_c": 1.4142135623730951,
    "public_artifact_alignment": "uct fields match the public VCHarness tree schema when selection_policy=uct; puct is an optional repo extension",
    "last_backpropagation": {
      "leaf": "official_k562_root_aido_gnn_embedding_mlp_p8_official_target_bilinear_head_495e575b",
      "reward": 0.48786869645118713,
      "path": [
        "official_k562_root_aido_gnn_embedding_mlp_p8_official_target_bilinear_head_495e575b",
        "official_k562_root_aido_gnn_embedding_mlp_p4_official_target_gene_head_d1c96042",
        "official_k562_root_aido_gnn_embedding_mlp"
      ],
      "path_length": 3
    }
  }
}